<plominodatabase id="iol_sp">
  <design>
    <element id="bo_parere_richiesta" title="Richiesta di parere" type="PlominoForm">
      <id type="Products.Archetypes.Field.StringField">bo_parere_richiesta</id>
      <onCreateDocument type="Products.Archetypes.Field.TextField"><![CDATA[parentDoc = context.getParentDatabase().getDocument(context.getItem('parent_document'))
if parentDoc:
    context.setItem('Plomino_Readers',parentDoc.getItem('Plomino_Readers'))]]></onCreateDocument>
      <onOpenDocument type="Products.Archetypes.Field.TextField"><![CDATA[]]></onOpenDocument>
      <beforeSaveDocument type="Products.Archetypes.Field.TextField"><![CDATA[]]></beforeSaveDocument>
      <onSaveDocument type="Products.Archetypes.Field.TextField"><![CDATA[parentDoc = context.getParentDatabase().getDocument(context.getItem('parent_document'))
if not parentDoc:
    context.plone_utils.addPortalMessage('Non esiste il documento padre','error')
    return 

if 'btn_stampa_comunicazione' in context.REQUEST.keys():
    if context.getItem('allegato_documento_richiesta_parere',{})=={}:
        context.getParentDatabase().resources.customscripts.stampaModulo(context,
            parent=parentDoc.getId(),
            parentform='sub_completa_'+parentDoc.getItem('iol_tipo_app'),
            model=context.getItem('modello_stampa_richiesta_parere'),
            app=context.getParentDatabase().getId().replace('iol_',''),
            grp='richiesta-parere',
            pdf=0,
            field='allegato_documento_richiesta_parere')
    return "%s/EditDocument" %context.absolute_url()

else:
    return parentDoc.absolute_url()]]></onSaveDocument>
      <onDeleteDocument type="Products.Archetypes.Field.TextField"><![CDATA[parentDoc = context.getParentDatabase().getDocument(context.getItem('parent_document'))
context.REQUEST.set('returnurl',parentDoc.absolute_url())]]></onDeleteDocument>
      <onSearch type="Products.Archetypes.Field.TextField"><![CDATA[]]></onSearch>
      <beforeCreateDocument type="Products.Archetypes.Field.TextField"><![CDATA[]]></beforeCreateDocument>
      <FormLayout type="Products.Archetypes.Field.TextField"><![CDATA[
<div class="iol-toolbar"></div>
<div class="v-content well">
<div class="row-fluid"><div class="span6">
<span class="plominoLabelClass">parere_ente_opt</span><span class="plominoFieldClass">parere_ente_opt</span>
</div></div>
<p><span class="plominoHidewhenClass">start:hw_no_parere_ente_altro</span></p>
<div class="row-fluid">
<div class="span6">
<span class="plominoLabelClass">parere_ente_altro</span><span class="plominoFieldClass">parere_ente_altro</span>
</div>
<div class="span6">
<span class="plominoLabelClass">parere_ente_altro_email</span><span class="plominoFieldClass">parere_ente_altro_email</span>
</div>
</div>
<p><span class="plominoHidewhenClass">end:hw_no_parere_ente_altro</span></p>
<div>
<span class="plominoLabelClass">oggetto_richiesta_parere</span><span class="plominoFieldClass">oggetto_richiesta_parere</span>
</div>
<span class="plominoHidewhenClass">start:hw_no_edit</span><div class="row-fluid">
<div class="span8">
<span class="plominoLabelClass">modello_stampa_richiesta_parere</span><span class="plominoFieldClass">modello_stampa_richiesta_parere</span>
</div>
<div class="span4">
<br><span class="plominoActionClass">btn_stampa_comunicazione</span>
</div>
</div>
<span class="plominoHidewhenClass">end:hw_no_edit</span><p><span class="plominoHidewhenClass">start:hw_new_comunicazione</span></p>
<p><span class="plominoFieldClass">istruzioni_richiesta_parere</span></p>
<div class="row-fluid">
<span class="plominoHidewhenClass">start:hw_no_istruttore_richiesta_parere</span><div class="span5">
<span class="plominoLabelClass">allegato_documento_richiesta_parere</span><span class="plominoFieldClass">allegato_documento_richiesta_parere</span>
</div>
<span class="plominoHidewhenClass">end:hw_no_istruttore_richiesta_parere</span><div class="span5">
<span class="plominoLabelClass">allegato_comunicazione_richiesta_parere</span><span class="plominoFieldClass">allegato_comunicazione_richiesta_parere</span>
</div>
<div class="span2">
<span class="plominoActionClass">btn_invia_comunicazione</span> <span class="plominoHidewhenClass">start:hw_no_data_comunicazione</span> <span class="plominoLabelClass">data_richiesta_parere</span><span class="plominoFieldClass">data_richiesta_parere</span> <span class="plominoHidewhenClass">end:hw_no_data_comunicazione</span>
</div>
</div>
<p><span class="plominoHidewhenClass">end:hw_new_comunicazione</span></p>
</div>
<p><span class="plominoFieldClass">parent_document</span></p>
]]></FormLayout>
      <FormMethod type="Products.Archetypes.Field.TextField"><![CDATA[Auto]]></FormMethod>
      <DocumentTitle type="Products.Archetypes.Field.TextField"><![CDATA['Richiesta parere %s' %context.getItem('parent_document')]]></DocumentTitle>
      <DynamicDocumentTitle type="Products.Archetypes.Field.BooleanField">False</DynamicDocumentTitle>
      <StoreDynamicDocumentTitle type="Products.Archetypes.Field.BooleanField">False</StoreDynamicDocumentTitle>
      <DocumentId type="Products.Archetypes.Field.TextField"><![CDATA['%s-p' %context.getItem('parent_document')]]></DocumentId>
      <ActionBarPosition type="Products.Archetypes.Field.StringField">TOP</ActionBarPosition>
      <HideDefaultActions type="Products.Archetypes.Field.BooleanField">True</HideDefaultActions>
      <HideInMenu type="Products.Archetypes.Field.BooleanField">True</HideInMenu>
      <isSearchForm type="Products.Archetypes.Field.BooleanField">False</isSearchForm>
      <isPage type="Products.Archetypes.Field.BooleanField">False</isPage>
      <SearchView type="Products.Archetypes.Field.StringField"/>
      <SearchFormula type="Products.Archetypes.Field.TextField"><![CDATA[]]></SearchFormula>
      <Position type="Products.Archetypes.Field.IntegerField"/>
      <ResourcesJS type="Products.Archetypes.Field.TextField"><![CDATA[]]></ResourcesJS>
      <ResourcesCSS type="Products.Archetypes.Field.TextField"><![CDATA[++resource++iol.document/css/bootstrap.min.css
++resource++iol.document/css/bootstrap-accessibile.min.css
++resource++iol.document/css/bootstrap-responsive.min.css
++resource++iol.document/css/iol.css
resources/iol-custom.css]]></ResourcesCSS>
      <excludeFromNav type="Products.Archetypes.Field.BooleanField">False</excludeFromNav>
      <elements>
        <element id="oggetto_richiesta_parere" title="Oggetto della comunicazione" type="PlominoField">
          <id type="Products.Archetypes.Field.StringField">oggetto_richiesta_parere</id>
          <FieldType type="Products.Archetypes.Field.StringField">TEXT</FieldType>
          <FieldMode type="Products.Archetypes.Field.StringField">EDITABLE</FieldMode>
          <Formula type="Products.Archetypes.Field.TextField"><![CDATA[]]></Formula>
          <FieldReadTemplate type="Products.Archetypes.Field.StringField"/>
          <FieldEditTemplate type="Products.Archetypes.Field.StringField"/>
          <Mandatory type="Products.Archetypes.Field.BooleanField">True</Mandatory>
          <ValidationFormula type="Products.Archetypes.Field.TextField"><![CDATA[]]></ValidationFormula>
          <ToBeIndexed type="Products.Archetypes.Field.BooleanField">False</ToBeIndexed>
          <IndexType type="Products.Archetypes.Field.StringField">DEFAULT</IndexType>
          <HTMLAttributesFormula type="Products.Archetypes.Field.TextField"><![CDATA[#if context.getItem('IOL_AVVISORIGETTO'):
#    return 'readonly']]></HTMLAttributesFormula>
          <params>
<param>
<value><array><data>
<value><struct>
<member>
<name>size</name>
<value><string>4</string></value>
</member>
</struct></value>
<value><struct>
<member>
<name>widget</name>
<value><string>TEXTAREA</string></value>
</member>
</struct></value>
</data></array></value>
</param>
</params>
        </element>
        <element id="comunicazione_richiesta_parere_opt" title="Allega la comunicazione firmata digitalmente" type="PlominoField">
          <id type="Products.Archetypes.Field.StringField">comunicazione_richiesta_parere_opt</id>
          <FieldType type="Products.Archetypes.Field.StringField">BOOLEAN</FieldType>
          <FieldMode type="Products.Archetypes.Field.StringField">EDITABLE</FieldMode>
          <Formula type="Products.Archetypes.Field.TextField"><![CDATA[]]></Formula>
          <FieldReadTemplate type="Products.Archetypes.Field.StringField"/>
          <FieldEditTemplate type="Products.Archetypes.Field.StringField"/>
          <Mandatory type="Products.Archetypes.Field.BooleanField">False</Mandatory>
          <ValidationFormula type="Products.Archetypes.Field.TextField"><![CDATA[]]></ValidationFormula>
          <ToBeIndexed type="Products.Archetypes.Field.BooleanField">False</ToBeIndexed>
          <IndexType type="Products.Archetypes.Field.StringField">DEFAULT</IndexType>
          <HTMLAttributesFormula type="Products.Archetypes.Field.TextField"><![CDATA['data-dhw=bo_parere_richiesta']]></HTMLAttributesFormula>
        </element>
        <element id="hw_no_allegato_comunicazione_richiesta_parere" title="hw_no_allegato_comunicazione_richiesta_parere" type="PlominoHidewhen">
          <id type="Products.Archetypes.Field.StringField">hw_no_allegato_comunicazione_richiesta_parere</id>
          <Formula type="Products.Archetypes.Field.TextField"><![CDATA[return not context.getItem('comunicazione_richiesta_parere_opt',False)]]></Formula>
          <isDynamicHidewhen type="Products.Archetypes.Field.BooleanField">True</isDynamicHidewhen>
        </element>
        <element id="data_richiesta_parere" title="Data invio richiesta" type="PlominoField">
          <id type="Products.Archetypes.Field.StringField">data_richiesta_parere</id>
          <FieldType type="Products.Archetypes.Field.StringField">DATETIME</FieldType>
          <FieldMode type="Products.Archetypes.Field.StringField">EDITABLE</FieldMode>
          <Formula type="Products.Archetypes.Field.TextField"><![CDATA[]]></Formula>
          <FieldReadTemplate type="Products.Archetypes.Field.StringField">IOL-DATETIMEFieldRead</FieldReadTemplate>
          <FieldEditTemplate type="Products.Archetypes.Field.StringField"/>
          <Mandatory type="Products.Archetypes.Field.BooleanField">False</Mandatory>
          <ValidationFormula type="Products.Archetypes.Field.TextField"><![CDATA[]]></ValidationFormula>
          <ToBeIndexed type="Products.Archetypes.Field.BooleanField">False</ToBeIndexed>
          <IndexType type="Products.Archetypes.Field.StringField">DEFAULT</IndexType>
          <HTMLAttributesFormula type="Products.Archetypes.Field.TextField"><![CDATA[return '''
data-datepicker-options='{"changeMonth": true, "changeYear": true, "minDate":"-110Y", "dateFormat": "dd/mm/yy", "yearRange": "-10:+10"}'
''']]></HTMLAttributesFormula>
          <params>
<param>
<value><array><data>
<value><struct>
<member>
<name>format</name>
<value><string>%d/%m/%Y</string></value>
</member>
</struct></value>
<value><struct>
<member>
<name>widget</name>
<value><string>JQUERY</string></value>
</member>
</struct></value>
</data></array></value>
</param>
</params>
        </element>
        <element id="modello_stampa_richiesta_parere" title="Seleziona un modello per la stampa" type="PlominoField">
          <id type="Products.Archetypes.Field.StringField">modello_stampa_richiesta_parere</id>
          <FieldType type="Products.Archetypes.Field.StringField">SELECTION</FieldType>
          <FieldMode type="Products.Archetypes.Field.StringField">EDITABLE</FieldMode>
          <Formula type="Products.Archetypes.Field.TextField"><![CDATA[]]></Formula>
          <FieldReadTemplate type="Products.Archetypes.Field.StringField"/>
          <FieldEditTemplate type="Products.Archetypes.Field.StringField"/>
          <Mandatory type="Products.Archetypes.Field.BooleanField">False</Mandatory>
          <ValidationFormula type="Products.Archetypes.Field.TextField"><![CDATA[]]></ValidationFormula>
          <ToBeIndexed type="Products.Archetypes.Field.BooleanField">False</ToBeIndexed>
          <IndexType type="Products.Archetypes.Field.StringField">DEFAULT</IndexType>
          <HTMLAttributesFormula type="Products.Archetypes.Field.TextField"><![CDATA[]]></HTMLAttributesFormula>
          <params>
<param>
<value><array><data>
<value><struct>
<member>
<name>dynamictableparam</name>
<value><string>'bPaginate': true,
'bLengthChange': true,
'bFilter': true,
'bSort': true,
'bInfo': true,
'bAutoWidth': false</string></value>
</member>
</struct></value>
<value><struct>
<member>
<name>selectionlistformula</name>
<value><string>return context.getPrintFolderContents(grp='richiesta-parere')
</string></value>
</member>
</struct></value>
</data></array></value>
</param>
</params>
        </element>
        <element id="allegato_documento_richiesta_parere" title="Documento creato" type="PlominoField">
          <id type="Products.Archetypes.Field.StringField">allegato_documento_richiesta_parere</id>
          <FieldType type="Products.Archetypes.Field.StringField">ATTACHMENT</FieldType>
          <FieldMode type="Products.Archetypes.Field.StringField">EDITABLE</FieldMode>
          <Formula type="Products.Archetypes.Field.TextField"><![CDATA[]]></Formula>
          <FieldReadTemplate type="Products.Archetypes.Field.StringField">IOL-ATTACHMENTIconFieldRead</FieldReadTemplate>
          <FieldEditTemplate type="Products.Archetypes.Field.StringField">IOL-ATTACHMENTFieldEdit</FieldEditTemplate>
          <Mandatory type="Products.Archetypes.Field.BooleanField">False</Mandatory>
          <ValidationFormula type="Products.Archetypes.Field.TextField"><![CDATA[]]></ValidationFormula>
          <ToBeIndexed type="Products.Archetypes.Field.BooleanField">False</ToBeIndexed>
          <IndexType type="Products.Archetypes.Field.StringField">DEFAULT</IndexType>
          <HTMLAttributesFormula type="Products.Archetypes.Field.TextField"><![CDATA[return'''
data-plugin = "iolUploadFile" data-plugin-options='{"emptyMessage":"Nessun file","maxsize":"3","filetype":["docx","odt"]}'
''']]></HTMLAttributesFormula>
          <params>
<param>
<value><array><data>
<value><struct>
<member>
<name>type</name>
<value><string>SINGLE</string></value>
</member>
</struct></value>
</data></array></value>
</param>
</params>
        </element>
        <element id="allegato_comunicazione_richiesta_parere" title="Comunicazione di richiesta parere" type="PlominoField">
          <id type="Products.Archetypes.Field.StringField">allegato_comunicazione_richiesta_parere</id>
          <FieldType type="Products.Archetypes.Field.StringField">ATTACHMENT</FieldType>
          <FieldMode type="Products.Archetypes.Field.StringField">EDITABLE</FieldMode>
          <Formula type="Products.Archetypes.Field.TextField"><![CDATA[]]></Formula>
          <FieldReadTemplate type="Products.Archetypes.Field.StringField">IOL-ATTACHMENTFieldRead</FieldReadTemplate>
          <FieldEditTemplate type="Products.Archetypes.Field.StringField">IOL-ATTACHMENTFieldEdit</FieldEditTemplate>
          <Mandatory type="Products.Archetypes.Field.BooleanField">False</Mandatory>
          <ValidationFormula type="Products.Archetypes.Field.TextField"><![CDATA[]]></ValidationFormula>
          <ToBeIndexed type="Products.Archetypes.Field.BooleanField">False</ToBeIndexed>
          <IndexType type="Products.Archetypes.Field.StringField">DEFAULT</IndexType>
          <HTMLAttributesFormula type="Products.Archetypes.Field.TextField"><![CDATA[return'''
data-plugin = "iolUploadFile" data-plugin-options='{"emptyMessage":"Nessun file"}'
''']]></HTMLAttributesFormula>
        </element>
        <element id="hw_no_edit" title="hw_no_edit" type="PlominoHidewhen">
          <id type="Products.Archetypes.Field.StringField">hw_no_edit</id>
          <Formula type="Products.Archetypes.Field.TextField"><![CDATA[not context.isEditMode() or context.getItem('allegato_documento_richiesta_parere',{})!={}]]></Formula>
          <isDynamicHidewhen type="Products.Archetypes.Field.BooleanField">False</isDynamicHidewhen>
        </element>
        <element id="hw_new_comunicazione" title="hw_new_comunicazione" type="PlominoHidewhen">
          <id type="Products.Archetypes.Field.StringField">hw_new_comunicazione</id>
          <Formula type="Products.Archetypes.Field.TextField"><![CDATA[context.getItem('oggetto_richiesta_parere')=='']]></Formula>
          <isDynamicHidewhen type="Products.Archetypes.Field.BooleanField">False</isDynamicHidewhen>
        </element>
        <element id="hw_no_data_comunicazione" title="hw_no_data_comunicazione" type="PlominoHidewhen">
          <id type="Products.Archetypes.Field.StringField">hw_no_data_comunicazione</id>
          <Formula type="Products.Archetypes.Field.TextField"><![CDATA[context.getItem('data_richiesta_parere')=='']]></Formula>
          <isDynamicHidewhen type="Products.Archetypes.Field.BooleanField">False</isDynamicHidewhen>
        </element>
        <element id="btn_save" title="Salva e continua &gt;&gt;" type="PlominoAction">
          <id type="Products.Archetypes.Field.StringField">btn_save</id>
          <ActionType type="Products.Archetypes.Field.StringField">SAVE</ActionType>
          <ActionDisplay type="Products.Archetypes.Field.StringField">BUTTON</ActionDisplay>
          <Content type="Products.Archetypes.Field.TextField"><![CDATA[]]></Content>
          <Hidewhen type="Products.Archetypes.Field.TextField"><![CDATA[return not context.isEditMode()]]></Hidewhen>
          <InActionBar type="Products.Archetypes.Field.BooleanField">True</InActionBar>
        </element>
        <element id="btn_cancel" title="Annulla" type="PlominoAction">
          <id type="Products.Archetypes.Field.StringField">btn_cancel</id>
          <ActionType type="Products.Archetypes.Field.StringField">REDIRECT</ActionType>
          <ActionDisplay type="Products.Archetypes.Field.StringField">BUTTON</ActionDisplay>
          <Content type="Products.Archetypes.Field.TextField"><![CDATA[parentDoc = context.getParentDatabase().getDocument(context.REQUEST.URL.split('/')[-3])  
if not parentDoc:
    parentDoc = context.getParentDatabase().getDocument(context.getItem('parent_document'))

return parentDoc.absolute_url()


try:
    if context.isNewDocument():
        parentDoc = context.getDocument(context.REQUEST.URL.split('/')[-3])  
    else:
        parentDoc = context.getParentDatabase().getDocument(context.getItem('parent_document'))
    return parentDoc.absolute_url()
except:
    pass]]></Content>
          <Hidewhen type="Products.Archetypes.Field.TextField"><![CDATA[return not context.isEditMode()]]></Hidewhen>
          <InActionBar type="Products.Archetypes.Field.BooleanField">True</InActionBar>
        </element>
        <element id="btn_elimina" title="Elimina" type="PlominoAction">
          <id type="Products.Archetypes.Field.StringField">btn_elimina</id>
          <ActionType type="Products.Archetypes.Field.StringField">CLOSE</ActionType>
          <ActionDisplay type="Products.Archetypes.Field.StringField">BUTTON</ActionDisplay>
          <Content type="Products.Archetypes.Field.TextField"><![CDATA[]]></Content>
          <Hidewhen type="Products.Archetypes.Field.TextField"><![CDATA[context.isNewDocument() or not context.isEditMode()]]></Hidewhen>
          <InActionBar type="Products.Archetypes.Field.BooleanField">True</InActionBar>
        </element>
        <element id="btn_invia_comunicazione" title="Invia la comunicazione &gt;&gt;" type="PlominoAction">
          <id type="Products.Archetypes.Field.StringField">btn_invia_comunicazione</id>
          <ActionType type="Products.Archetypes.Field.StringField">PYTHON</ActionType>
          <ActionDisplay type="Products.Archetypes.Field.StringField">BUTTON</ActionDisplay>
          <Content type="Products.Archetypes.Field.TextField"><![CDATA[parentDoc = context.getParentDatabase().getDocument(context.getItem('parent_document'))
parentDoc.doAction('richiedi_parere')
context.setItem('data_comunicazione_richiesta_parere',Now())
#Allineo i readers
settings = context.getParentDatabase().resources.customscripts.getDocSettings()
readers = [str(context.getItem('destinatario_parere')),str(settings.getItem('grp_istruttori'))]
context.setItem('Plomino_Readers',readers)  
context.setItem('Plomino_Authors',[str(settings.getItem('grp_istruttori'))])
context.getParentDatabase().getIndex().indexDocument(context)

return parentDoc.absolute_url()]]></Content>
          <Hidewhen type="Products.Archetypes.Field.TextField"><![CDATA[try:
    return context.isEditMode() or plominoDocument.getItem('data_comunicazione_richiesta_parere')!='' or context.getItem('allegato_comunicazione_richiesta_parere',{})=={}
except:
    return True]]></Hidewhen>
          <InActionBar type="Products.Archetypes.Field.BooleanField">False</InActionBar>
        </element>
        <element id="btn_stampa_comunicazione" title="&gt;&gt; Crea il documento" type="PlominoAction">
          <id type="Products.Archetypes.Field.StringField">btn_stampa_comunicazione</id>
          <ActionType type="Products.Archetypes.Field.StringField">SAVE</ActionType>
          <ActionDisplay type="Products.Archetypes.Field.StringField">SUBMIT</ActionDisplay>
          <Content type="Products.Archetypes.Field.TextField"><![CDATA[]]></Content>
          <Hidewhen type="Products.Archetypes.Field.TextField"><![CDATA[try:
    return not context.isEditMode() or context.getItem('allegato_documento_richiesta_parere',{})!={}
except:
    return False]]></Hidewhen>
          <InActionBar type="Products.Archetypes.Field.BooleanField">False</InActionBar>
        </element>
        <element id="parent_document" title="parent_document" type="PlominoField">
          <id type="Products.Archetypes.Field.StringField">parent_document</id>
          <FieldType type="Products.Archetypes.Field.StringField">TEXT</FieldType>
          <FieldMode type="Products.Archetypes.Field.StringField">EDITABLE</FieldMode>
          <Formula type="Products.Archetypes.Field.TextField"><![CDATA[context.REQUEST.URL.split('/')[-3]]]></Formula>
          <FieldReadTemplate type="Products.Archetypes.Field.StringField"/>
          <FieldEditTemplate type="Products.Archetypes.Field.StringField"/>
          <Mandatory type="Products.Archetypes.Field.BooleanField">True</Mandatory>
          <ValidationFormula type="Products.Archetypes.Field.TextField"><![CDATA[]]></ValidationFormula>
          <ToBeIndexed type="Products.Archetypes.Field.BooleanField">True</ToBeIndexed>
          <IndexType type="Products.Archetypes.Field.StringField">DEFAULT</IndexType>
          <HTMLAttributesFormula type="Products.Archetypes.Field.TextField"><![CDATA[]]></HTMLAttributesFormula>
          <params>
<param>
<value><array><data>
<value><struct>
<member>
<name>widget</name>
<value><string>HIDDEN</string></value>
</member>
</struct></value>
</data></array></value>
</param>
</params>
        </element>
        <element id="parere_ente_opt" title="Parere / accertamento richiesto a Ente / Ufficio" type="PlominoField">
          <id type="Products.Archetypes.Field.StringField">parere_ente_opt</id>
          <FieldType type="Products.Archetypes.Field.StringField">SELECTION</FieldType>
          <FieldMode type="Products.Archetypes.Field.StringField">EDITABLE</FieldMode>
          <Formula type="Products.Archetypes.Field.TextField"><![CDATA[]]></Formula>
          <FieldReadTemplate type="Products.Archetypes.Field.StringField">SELECTIONFieldReadCheck</FieldReadTemplate>
          <FieldEditTemplate type="Products.Archetypes.Field.StringField"/>
          <Mandatory type="Products.Archetypes.Field.BooleanField">True</Mandatory>
          <ValidationFormula type="Products.Archetypes.Field.TextField"><![CDATA[]]></ValidationFormula>
          <ToBeIndexed type="Products.Archetypes.Field.BooleanField">False</ToBeIndexed>
          <IndexType type="Products.Archetypes.Field.StringField">DEFAULT</IndexType>
          <HTMLAttributesFormula type="Products.Archetypes.Field.TextField"><![CDATA[]]></HTMLAttributesFormula>
          <params>
<param>
<value><array><data>
<value><struct>
<member>
<name>dynamictableparam</name>
<value><string>'bPaginate': true,
'bLengthChange': true,
'bFilter': true,
'bSort': true,
'bInfo': true,
'bAutoWidth': false</string></value>
</member>
</struct></value>
<value><struct>
<member>
<name>selectionlistformula</name>
<value><string>from iol.document.plomino_utils import elencoUtentiGruppi
settings = context.getParentDatabase().resources.customscripts.getDocSettings()
grp = settings.getItem('grp_pareri')
if grp:
    return ['|'] + elencoUtentiGruppi(context,groups=[grp])
else:
    return []</string></value>
</member>
</struct></value>
</data></array></value>
</param>
</params>
        </element>
        <element id="parere_protocollo_opt" title="Il parere espresso:" type="PlominoField">
          <id type="Products.Archetypes.Field.StringField">parere_protocollo_opt</id>
          <FieldType type="Products.Archetypes.Field.StringField">SELECTION</FieldType>
          <FieldMode type="Products.Archetypes.Field.StringField">EDITABLE</FieldMode>
          <Formula type="Products.Archetypes.Field.TextField"><![CDATA[]]></Formula>
          <FieldReadTemplate type="Products.Archetypes.Field.StringField">SELECTIONFieldReadCheck</FieldReadTemplate>
          <FieldEditTemplate type="Products.Archetypes.Field.StringField"/>
          <Mandatory type="Products.Archetypes.Field.BooleanField">True</Mandatory>
          <ValidationFormula type="Products.Archetypes.Field.TextField"><![CDATA[]]></ValidationFormula>
          <ToBeIndexed type="Products.Archetypes.Field.BooleanField">False</ToBeIndexed>
          <IndexType type="Products.Archetypes.Field.StringField">DEFAULT</IndexType>
          <HTMLAttributesFormula type="Products.Archetypes.Field.TextField"><![CDATA[]]></HTMLAttributesFormula>
          <params>
<param>
<value><array><data>
<value><struct>
<member>
<name>dynamictableparam</name>
<value><string>'bPaginate': true,
'bLengthChange': true,
'bFilter': true,
'bSort': true,
'bInfo': true,
'bAutoWidth': false</string></value>
</member>
</struct></value>
<value><struct>
<member>
<name>selectionlistformula</name>
<value><string>['SELEZIONA OPZIONE DI PROTOCOLLAZIONE =&gt;|x','Dovrà essere protocollato in ingresso|1','NON dovrà essere protocollato in ingresso|2','Verrà protocollato manualmente|3']</string></value>
</member>
</struct></value>
<value><struct>
<member>
<name>separator</name>
<value><string>&lt;br&gt;</string></value>
</member>
</struct></value>
<value><struct>
<member>
<name>widget</name>
<value><string>SELECT</string></value>
</member>
</struct></value>
</data></array></value>
</param>
</params>
        </element>
        <element id="hw_no_parere_ente_altro" title="hw_no_parere_ente_altro" type="PlominoHidewhen">
          <id type="Products.Archetypes.Field.StringField">hw_no_parere_ente_altro</id>
          <Formula type="Products.Archetypes.Field.TextField"><![CDATA[context.getItem('parere_ente_opt')!='altro']]></Formula>
          <isDynamicHidewhen type="Products.Archetypes.Field.BooleanField">True</isDynamicHidewhen>
        </element>
        <element id="parere_ente_altro" title="Altro destinatario della richiesta" type="PlominoField">
          <id type="Products.Archetypes.Field.StringField">parere_ente_altro</id>
          <FieldType type="Products.Archetypes.Field.StringField">TEXT</FieldType>
          <FieldMode type="Products.Archetypes.Field.StringField">EDITABLE</FieldMode>
          <Formula type="Products.Archetypes.Field.TextField"><![CDATA[]]></Formula>
          <FieldReadTemplate type="Products.Archetypes.Field.StringField"/>
          <FieldEditTemplate type="Products.Archetypes.Field.StringField"/>
          <Mandatory type="Products.Archetypes.Field.BooleanField">True</Mandatory>
          <ValidationFormula type="Products.Archetypes.Field.TextField"><![CDATA[]]></ValidationFormula>
          <ToBeIndexed type="Products.Archetypes.Field.BooleanField">False</ToBeIndexed>
          <IndexType type="Products.Archetypes.Field.StringField">DEFAULT</IndexType>
          <HTMLAttributesFormula type="Products.Archetypes.Field.TextField"><![CDATA[if context.isDocument():
    return 'readonly']]></HTMLAttributesFormula>
        </element>
        <element id="parere_ente_altro_email" title="Indirizzo e-mail" type="PlominoField">
          <id type="Products.Archetypes.Field.StringField">parere_ente_altro_email</id>
          <FieldType type="Products.Archetypes.Field.StringField">TEXT</FieldType>
          <FieldMode type="Products.Archetypes.Field.StringField">EDITABLE</FieldMode>
          <Formula type="Products.Archetypes.Field.TextField"><![CDATA[]]></Formula>
          <FieldReadTemplate type="Products.Archetypes.Field.StringField"/>
          <FieldEditTemplate type="Products.Archetypes.Field.StringField"/>
          <Mandatory type="Products.Archetypes.Field.BooleanField">True</Mandatory>
          <ValidationFormula type="Products.Archetypes.Field.TextField"><![CDATA[]]></ValidationFormula>
          <ToBeIndexed type="Products.Archetypes.Field.BooleanField">False</ToBeIndexed>
          <IndexType type="Products.Archetypes.Field.StringField">DEFAULT</IndexType>
          <HTMLAttributesFormula type="Products.Archetypes.Field.TextField"><![CDATA[]]></HTMLAttributesFormula>
        </element>
        <element id="destinatario_parere" title="destinatario_parere" type="PlominoField">
          <id type="Products.Archetypes.Field.StringField">destinatario_parere</id>
          <FieldType type="Products.Archetypes.Field.StringField">TEXT</FieldType>
          <FieldMode type="Products.Archetypes.Field.StringField">COMPUTEDONSAVE</FieldMode>
          <Formula type="Products.Archetypes.Field.TextField"><![CDATA[if context.getItem('parere_ente_opt')=='altro':
    return context.getItem('parere_ente_altro_email')
else:
    return context.getItem('parere_ente_opt')]]></Formula>
          <FieldReadTemplate type="Products.Archetypes.Field.StringField"/>
          <FieldEditTemplate type="Products.Archetypes.Field.StringField"/>
          <Mandatory type="Products.Archetypes.Field.BooleanField">False</Mandatory>
          <ValidationFormula type="Products.Archetypes.Field.TextField"><![CDATA[]]></ValidationFormula>
          <ToBeIndexed type="Products.Archetypes.Field.BooleanField">False</ToBeIndexed>
          <IndexType type="Products.Archetypes.Field.StringField">DEFAULT</IndexType>
          <HTMLAttributesFormula type="Products.Archetypes.Field.TextField"><![CDATA[]]></HTMLAttributesFormula>
        </element>
        <element id="hw_no_istruttore_richiesta_parere" title="hw_no_istruttore_richiesta_parere" type="PlominoHidewhen">
          <id type="Products.Archetypes.Field.StringField">hw_no_istruttore_richiesta_parere</id>
          <Formula type="Products.Archetypes.Field.TextField"><![CDATA[return not 'PlominoEditor' in context.getCurrentUserRights()]]></Formula>
          <isDynamicHidewhen type="Products.Archetypes.Field.BooleanField">False</isDynamicHidewhen>
        </element>
        <element id="istruzioni_richiesta_parere" title="istruzioni_richiesta_parere" type="PlominoField">
          <id type="Products.Archetypes.Field.StringField">istruzioni_richiesta_parere</id>
          <FieldType type="Products.Archetypes.Field.StringField">TEXT</FieldType>
          <FieldMode type="Products.Archetypes.Field.StringField">DISPLAY</FieldMode>
          <Formula type="Products.Archetypes.Field.TextField"><![CDATA[if context.getItem('allegato_comunicazione_richiesta_parere',{})=={}:
    return '''<div class="alert alert-info">Allegare la comunicazione per abilitare l'invio della richiesta</div>'''
elif context.getItem('data_comunicazione_richiesta_parere')!='':
    return '''<div class="alert alert-success"><strong>Comunicazione di richiesta parere inviata in data %s</strong></div>''' %DateToString(context.getItem('data_comunicazione_richiesta_parere'),format="%d/%m/%Y %H:%M")]]></Formula>
          <FieldReadTemplate type="Products.Archetypes.Field.StringField">TEXTFieldCell</FieldReadTemplate>
          <FieldEditTemplate type="Products.Archetypes.Field.StringField"/>
          <Mandatory type="Products.Archetypes.Field.BooleanField">False</Mandatory>
          <ValidationFormula type="Products.Archetypes.Field.TextField"><![CDATA[]]></ValidationFormula>
          <ToBeIndexed type="Products.Archetypes.Field.BooleanField">False</ToBeIndexed>
          <IndexType type="Products.Archetypes.Field.StringField">DEFAULT</IndexType>
          <HTMLAttributesFormula type="Products.Archetypes.Field.TextField"><![CDATA[]]></HTMLAttributesFormula>
        </element>
      </elements>
    </element>
  </design>
</plominodatabase>
